madjax/__init__.py
madjax-0.0.1.dist-info/METADATA
madjax-0.0.1.dist-info/WHEEL
madjax-0.0.1.dist-info/top_level.txt
madjax-0.0.1.dist-info/RECORD
