Metadata-Version: 2.1
Name: madjax
Version: 0.0.1
Summary: differentiable matrix elements
Home-page: https://github.com/lukasheinrich/madjax
Author: Lukas Heinrich, Michael Kagan
Author-email: lukas.heinrich@cern.ch, mkagan@cern.ch
License: Apache
Keywords: physics autodifferentiation
Platform: UNKNOWN
Classifier: Programming Language :: Python :: 3
Classifier: Programming Language :: Python :: 3.6
Classifier: Programming Language :: Python :: 3.7
Requires-Python: >=3.6
Requires-Dist: jax (>0.1.51,~=0.1)
Requires-Dist: jaxlib (>0.1.33,~=0.1)
Provides-Extra: complete
Requires-Dist: bumpversion ; extra == 'complete'
Requires-Dist: ipython ; extra == 'complete'
Requires-Dist: ipywidgets ; extra == 'complete'
Requires-Dist: m2r ; extra == 'complete'
Requires-Dist: nbdime ; extra == 'complete'
Requires-Dist: nbsphinx ; extra == 'complete'
Requires-Dist: papermill (~=1.0) ; extra == 'complete'
Requires-Dist: pre-commit ; extra == 'complete'
Requires-Dist: pydocstyle ; extra == 'complete'
Requires-Dist: pyflakes ; extra == 'complete'
Requires-Dist: pytest (~=3.5) ; extra == 'complete'
Requires-Dist: sphinx ; extra == 'complete'
Requires-Dist: sphinx-click ; extra == 'complete'
Requires-Dist: sphinx-issues ; extra == 'complete'
Requires-Dist: sphinx-rtd-theme ; extra == 'complete'
Requires-Dist: sphinxcontrib-bibtex ; extra == 'complete'
Requires-Dist: twine ; extra == 'complete'
Requires-Dist: black ; (python_version >= "3.6") and extra == 'complete'
Provides-Extra: develop
Requires-Dist: bumpversion ; extra == 'develop'
Requires-Dist: ipython ; extra == 'develop'
Requires-Dist: ipywidgets ; extra == 'develop'
Requires-Dist: m2r ; extra == 'develop'
Requires-Dist: nbdime ; extra == 'develop'
Requires-Dist: nbsphinx ; extra == 'develop'
Requires-Dist: papermill (~=1.0) ; extra == 'develop'
Requires-Dist: pre-commit ; extra == 'develop'
Requires-Dist: pydocstyle ; extra == 'develop'
Requires-Dist: pyflakes ; extra == 'develop'
Requires-Dist: pytest (~=3.5) ; extra == 'develop'
Requires-Dist: sphinx ; extra == 'develop'
Requires-Dist: sphinx-click ; extra == 'develop'
Requires-Dist: sphinx-issues ; extra == 'develop'
Requires-Dist: sphinx-rtd-theme ; extra == 'develop'
Requires-Dist: sphinxcontrib-bibtex ; extra == 'develop'
Requires-Dist: twine ; extra == 'develop'
Requires-Dist: black ; (python_version >= "3.6") and extra == 'develop'
Provides-Extra: docs
Requires-Dist: ipywidgets ; extra == 'docs'
Requires-Dist: m2r ; extra == 'docs'
Requires-Dist: nbsphinx ; extra == 'docs'
Requires-Dist: sphinx ; extra == 'docs'
Requires-Dist: sphinx-click ; extra == 'docs'
Requires-Dist: sphinx-issues ; extra == 'docs'
Requires-Dist: sphinx-rtd-theme ; extra == 'docs'
Requires-Dist: sphinxcontrib-bibtex ; extra == 'docs'
Provides-Extra: test
Requires-Dist: papermill (~=1.0) ; extra == 'test'
Requires-Dist: pydocstyle ; extra == 'test'
Requires-Dist: pyflakes ; extra == 'test'
Requires-Dist: pytest (~=3.5) ; extra == 'test'
Requires-Dist: black ; (python_version >= "3.6") and extra == 'test'
